nepali_number_to_word/__init__.py
nepali_number_to_word/constants.py
nepali_number_to_word/converter.py
nepali_number_to_word-0.1.3.dist-info/METADATA
nepali_number_to_word-0.1.3.dist-info/WHEEL
nepali_number_to_word-0.1.3.dist-info/licenses/LICENSE
nepali_number_to_word-0.1.3.dist-info/RECORD
