Metadata-Version: 2.4
Name: nepali-number-to-word
Version: 0.1.3
Summary: A Python package to convert numbers to Nepali words
Author: Manisha Bhandari
License: MIT
License-File: LICENSE
Requires-Python: >=3.8
Requires-Dist: pre-commit>=3.5.0
Requires-Dist: pytest>=8.3.5
